raino_mcpserver_demo/__init__.py
raino_mcpserver_demo-0.1.0.dist-info/METADATA
raino_mcpserver_demo-0.1.0.dist-info/WHEEL
raino_mcpserver_demo-0.1.0.dist-info/entry_points.txt
raino_mcpserver_demo-0.1.0.dist-info/RECORD
